marley/__init__.py
marley/__main__.py
marley/commanding.py
marley/constants.py
marley/logging_setup.py
marley/marley_swank_database.py
marley/pycompat.py
marley/sharknadoing.py
marley/utils.py
marley/arezzo/__init__.py
marley/arezzo/core.py
marley/arezzo/user_sessioning.py
marley/arezzo/arezzo/dist/favicon.ico
marley/arezzo/arezzo/dist/index.html
marley/arezzo/arezzo/dist/css/app.e77d4233.css
marley/arezzo/arezzo/dist/img/loading.1ac21cc0.gif
marley/arezzo/arezzo/dist/js/app.4f8849d2.js
marley/arezzo/arezzo/dist/js/app.4f8849d2.js.map
marley/arezzo/arezzo/dist/js/chunk-vendors.138df1ae.js
marley/arezzo/arezzo/dist/js/chunk-vendors.138df1ae.js.map
marley/arezzo/arezzo/src/App.vue
marley/arezzo/arezzo/src/main.js
marley/arezzo/arezzo/src/assets/empty_star.png
marley/arezzo/arezzo/src/assets/full_star.png
marley/arezzo/arezzo/src/assets/loading.gif
marley/arezzo/arezzo/src/assets/logo.png
marley/arezzo/arezzo/src/components/Swank.vue
marley/arezzo/arezzo/src/components/SwankFieldValue.vue
marley/arezzo/arezzo/src/libraries/drilling.js
marley/arezzo/arezzo/src/libraries/savviness.js
marley/arezzo/arezzo/src/libraries/savviness.test.js
marley/arezzo/arezzo/src/router/index.js
marley/arezzo/arezzo/src/services/ArezzoService.js
marley/arezzo/arezzo/src/services/JamService.js
marley/arezzo/arezzo/src/store/index.js
marley/arezzo/arezzo/src/views/About.vue
marley/arezzo/arezzo/src/views/Home.vue
marley/arezzo/arezzo/src/views/SwankTrail.vue
marley/gamey/__init__.py
marley/gamey/aggregating.py
marley/gamey/base.py
marley/gamey/exceptions.py
marley/gamey/gamey_swanking.py
marley/gamey/gaming.py
marley/gamey/model_based.py
marley/gamey/model_free.py
marley/gamey/policing.py
marley/gamey/utils/__init__.py
marley/gamey/utils/chain_space.py
marley/gamey/utils/iterating.py
marley/gamey/utils/weak_key_identity_dict.py
marley/jamswank/__init__.py
marley/jamswank/file_locking/__init__.py
marley/jamswank/file_locking/file_locking.py
marley/jamswank/jamming/__init__.py
marley-0.5.2.dist-info/AUTHORS
marley-0.5.2.dist-info/LICENSE
marley-0.5.2.dist-info/METADATA
marley-0.5.2.dist-info/WHEEL
marley-0.5.2.dist-info/entry_points.txt
marley-0.5.2.dist-info/top_level.txt
marley-0.5.2.dist-info/RECORD
