Metadata-Version: 2.1
Name: marley
Version: 0.5.2
Summary: Marley - A framework for multi-agent reinforcment learning
Home-page: https://github.com/cool-RR/marley
Author: Ram Rachum
Author-email: ram@rachum.com
License: UNKNOWN
Platform: UNKNOWN
Classifier: Intended Audience :: Developers
Classifier: Intended Audience :: Science/Research
Classifier: Programming Language :: Python :: 3.8
Classifier: Programming Language :: Python :: 3.9
Classifier: Programming Language :: Python :: 3.10
Classifier: Programming Language :: Python :: Implementation :: CPython
Classifier: License :: OSI Approved :: MIT License
Classifier: Operating System :: OS Independent
Classifier: Topic :: Scientific/Engineering :: Artificial Intelligence
Classifier: Topic :: Scientific/Engineering :: Artificial Life
Requires-Python: >=3.8
License-File: LICENSE
License-File: AUTHORS
Requires-Dist: Flask-Cors (==3.0.10)
Requires-Dist: Flask (>=2.0.1)
Requires-Dist: altair-saver (>=0.5.0)
Requires-Dist: altair (>=4.1.0)
Requires-Dist: bidict (>=0.21.3)
Requires-Dist: click (>=8.0.1)
Requires-Dist: filelock (>=3.0.12)
Requires-Dist: h5py (>=3.1.0)
Requires-Dist: immutabledict (>=2.2.0)
Requires-Dist: more-itertools (>=8.10.0)
Requires-Dist: networkx (>=2.6.3)
Requires-Dist: numpy (>=1.19.5)
Requires-Dist: pyfakefs (>=4.5.1)
Requires-Dist: requests (>=2.26.0)
Requires-Dist: scipy (>=1.7.1)
Requires-Dist: tensorflow (>=2.6.0)
Provides-Extra: tests
Requires-Dist: pytest-xdist ; extra == 'tests'
Requires-Dist: pytest-html ; extra == 'tests'
Requires-Dist: pytest ; extra == 'tests'
